{
	"title": "see-base",
	"version": "0.4.2.3",
	"doctype": "HTML5",
	"thumbnail": "thumbnail.png",
	"author": "kr0l, Talvi und die ganzen anderen Dudes",
	"options": [
		{
			"label": "Farben",
			"type": "group",
			"options": [
				{
					"label": "Hintergrundfarbe",
					"name": "bodyBackgroundColor",
					"type": "color",
					"default": "#050d10"
				},
				{
					"label": "Titelfarbe",
					"name": "h1Color",
					"type": "color",
					"default": "#3c4bc5"
				},
				{
					"label": "Navigationsfarbe",
					"name": "navColor",
					"type": "color",
					"default": "#1c5c5c"
				},
				{
					"label": "Rahmenfarbe",
					"name": "borderColor",
					"type": "color",
					"default": "#302a79"
				},
				{
					"label": "Textfarbe",
					"name": "textColor",
					"type": "color",
					"default": "#97dfeb"
				},
				{
					"label": "Fußleistenfarbe",
					"name": "footerColor",
					"type": "color",
					"default": "#3c4bc5"
				}
			]
		},
		{
			"label": "Seitenoptik",
			"type": "group",
			"options": [
				{
					"label": "Seitenleisten Anordnung",
					"name": "asidePosition",
					"type": "select",
					"values": ["links", "rechts"],
					"default": "rechts"
				}
			]
		}
	]
}
